napari_nibabel/__init__.py
napari_nibabel/_reader.py
napari_nibabel/_version.py
napari_nibabel/napari.yaml
napari_nibabel-0.1.0.dist-info/LICENSE
napari_nibabel-0.1.0.dist-info/METADATA
napari_nibabel-0.1.0.dist-info/WHEEL
napari_nibabel-0.1.0.dist-info/entry_points.txt
napari_nibabel-0.1.0.dist-info/top_level.txt
napari_nibabel-0.1.0.dist-info/RECORD
